pyinstaller_extractor/__main__.py
pyinstaller_extractor/version.py
pyinstaller_extractor-1.0.2.dist-info/LICENSE
pyinstaller_extractor-1.0.2.dist-info/METADATA
pyinstaller_extractor-1.0.2.dist-info/WHEEL
pyinstaller_extractor-1.0.2.dist-info/entry_points.txt
pyinstaller_extractor-1.0.2.dist-info/top_level.txt
pyinstaller_extractor-1.0.2.dist-info/RECORD
