Metadata-Version: 2.1
Name: pyinstaller-extractor
Version: 1.0.2
Summary: Pyinstaller Extractor
Home-page: https://github.com/khiemdoan/pyinstaller_extractor
Author: Khiem Doan
Author-email: doankhiem.crazy@gmail.com
License: LGPL-2.1 License
Platform: UNKNOWN
Classifier: Development Status :: 5 - Production/Stable
Classifier: Environment :: Console
Classifier: Intended Audience :: Developers
Classifier: Natural Language :: English
Classifier: Operating System :: MacOS
Classifier: Operating System :: Microsoft :: Windows
Classifier: Operating System :: POSIX :: Linux
Classifier: Operating System :: OS Independent
Classifier: Programming Language :: Python
Classifier: Programming Language :: Python :: 3
Classifier: Programming Language :: Python :: 3.6
Classifier: Programming Language :: Python :: 3.7
Classifier: Programming Language :: Python :: 3.8
Classifier: Programming Language :: Python :: 3.9
Classifier: Programming Language :: Python :: 3.10
Classifier: Topic :: Utilities
Requires-Dist: pyinstaller
Requires-Dist: uncompyle6
Requires-Dist: xdis
